EasyModbusSilaaCooling/__init__.py
EasyModbusSilaaCooling/easyModbusGUI.py
EasyModbusSilaaCooling/modbusClient.py
EasyModbusSilaaCooling/modbusException.py
EasyModbusSilaaCooling-1.0.6.dist-info/LICENSE
EasyModbusSilaaCooling-1.0.6.dist-info/METADATA
EasyModbusSilaaCooling-1.0.6.dist-info/WHEEL
EasyModbusSilaaCooling-1.0.6.dist-info/top_level.txt
EasyModbusSilaaCooling-1.0.6.dist-info/RECORD
