Metadata-Version: 2.1
Name: EasyModbusSilaaCooling
Version: 1.0.6
Summary: A modification of the existing EasyModbus-package version 1.2.6 by Stefan Rossmann of Rossmann Engineering
Home-page: https://gogs.es-lab.de/SilaaCooling/Simulationsmodell_SilaaCooling/src/master/Helios%20Modbus
Author: ['Alexander Teubert', 'Stefan Rossmann']
License: UNKNOWN
Platform: UNKNOWN
Classifier: Programming Language :: Python :: 3
Classifier: Operating System :: OS Independent
Classifier: License :: OSI Approved :: GNU General Public License v3 (GPLv3)
Classifier: Natural Language :: English
Requires-Python: >=3.5.2
Requires-Dist: pyserial
Requires-Dist: easymodbus
